gpm/__init__.py
gpm/__main__.py
gpm-1.0.0.dist-info/DESCRIPTION.rst
gpm-1.0.0.dist-info/METADATA
gpm-1.0.0.dist-info/RECORD
gpm-1.0.0.dist-info/WHEEL
gpm-1.0.0.dist-info/metadata.json
gpm-1.0.0.dist-info/top_level.txt
